box/bin/__init__.py
box/bin/compile.py
box/bin/shell/__init__.py
box/bin/shell/shell.py
box/bin/shell/types.py
box/bin/ssh.py
box/bot/__init__.py
box/cli/__main__.py
box/cli/box.py
box/poe/pyproject.toml
box/sys/__init__.py
box/sys/debug.py
box/top/__init__.py
box/typ/__init__.py
box/typ/obj/__init__.py
box/typ/obj/str.py
box/vnv/__init__.py
pyproject.toml
readme.md
boxe-0.1.3.dist-info/METADATA
boxe-0.1.3.dist-info/WHEEL
boxe-0.1.3.dist-info/entry_points.txt
boxe-0.1.3.dist-info/RECORD
