Metadata-Version: 2.1
Name: boxe
Version: 0.1.3
Summary: 
Author: Phillip Sitbon
Author-email: phillip.sitbon@gmail.com
Requires-Python: >=3.11,<4.0
Classifier: Programming Language :: Python :: 3
Classifier: Programming Language :: Python :: 3.11
Requires-Dist: fabric (>=3.0.1,<4.0.0)
Requires-Dist: invocations (>=3.3.0,<4.0.0)
Requires-Dist: invoke (>=2.1.2,<3.0.0)
Requires-Dist: poethepoet (>=0.20.0,<0.21.0)
Requires-Dist: poetry (>=1.5.0,<2.0.0)
Requires-Dist: pytomlpp (>=1.0.13,<2.0.0)
